pycrdt_flow/__init__.py
pycrdt_flow/log.py
pycrdt_flow/permission.py
pycrdt_flow/backend/__init__.py
pycrdt_flow/backend/alembic.ini
pycrdt_flow/backend/app.py
pycrdt_flow/backend/auth.py
pycrdt_flow/backend/cli.py
pycrdt_flow/backend/config.py
pycrdt_flow/backend/daemon.py
pycrdt_flow/backend/dbutils.py
pycrdt_flow/backend/envs.py
pycrdt_flow/backend/manager.py
pycrdt_flow/backend/orm.py
pycrdt_flow/backend/rds.py
pycrdt_flow/backend/alembic/README
pycrdt_flow/backend/alembic/env.py
pycrdt_flow/backend/alembic/script.py.mako
pycrdt_flow/backend/alembic/versions/DO_NOT_DELETE
pycrdt_flow-0.0.6.dist-info/METADATA
pycrdt_flow-0.0.6.dist-info/WHEEL
pycrdt_flow-0.0.6.dist-info/entry_points.txt
pycrdt_flow-0.0.6.dist-info/licenses/LICENSE
pycrdt_flow-0.0.6.dist-info/RECORD
