Metadata-Version: 2.3
Name: pycrdt_flow
Version: 0.0.6
Summary: A CRDT lib and backend for react flow
Project-URL: Source, https://github.com/wh1isper/pycrdt_flow
Author-email: wh1isper <jizhongsheng957@gmail.com>
License: BSD 3-Clause License
License-File: LICENSE
Keywords: CRDT,pycrdt_flow,react,react-flow
Classifier: Programming Language :: Python :: 3
Classifier: Programming Language :: Python :: 3.10
Classifier: Programming Language :: Python :: 3.11
Classifier: Programming Language :: Python :: 3.12
Requires-Python: >=3.10
Requires-Dist: loguru
Requires-Dist: pycrdt
Requires-Dist: python-jose[cryptography]
Provides-Extra: docs
Requires-Dist: autodoc-pydantic; extra == 'docs'
Requires-Dist: pydata-sphinx-theme; extra == 'docs'
Requires-Dist: sphinx; extra == 'docs'
Requires-Dist: sphinx-click; extra == 'docs'
Provides-Extra: service
Requires-Dist: alembic; extra == 'service'
Requires-Dist: asyncpg; extra == 'service'
Requires-Dist: click; extra == 'service'
Requires-Dist: fastapi; extra == 'service'
Requires-Dist: importlib-metadata; extra == 'service'
Requires-Dist: psycopg2-binary; extra == 'service'
Requires-Dist: pydantic<3,>=2; extra == 'service'
Requires-Dist: redis>=4.2.0rc1; extra == 'service'
Requires-Dist: sqlalchemy[asyncio]; extra == 'service'
Requires-Dist: uvicorn[standard]; extra == 'service'
Provides-Extra: test
Requires-Dist: alembic; extra == 'test'
Requires-Dist: asyncpg; extra == 'test'
Requires-Dist: click; extra == 'test'
Requires-Dist: docker; extra == 'test'
Requires-Dist: fastapi; extra == 'test'
Requires-Dist: importlib-metadata; extra == 'test'
Requires-Dist: psycopg2-binary; extra == 'test'
Requires-Dist: pydantic<3,>=2; extra == 'test'
Requires-Dist: pytest; extra == 'test'
Requires-Dist: pytest-asyncio; extra == 'test'
Requires-Dist: pytest-cov; extra == 'test'
Requires-Dist: redis>=4.2.0rc1; extra == 'test'
Requires-Dist: sqlalchemy[asyncio]; extra == 'test'
Requires-Dist: uvicorn[standard]; extra == 'test'
